pheval_kghg/__init__.py
pheval_kghg/kghg.py
pheval_kghg/runner.py
pheval_kghg/test_configs/config.yaml
pheval_kghg-0.0.0.dist-info/LICENSE
pheval_kghg-0.0.0.dist-info/METADATA
pheval_kghg-0.0.0.dist-info/WHEEL
pheval_kghg-0.0.0.dist-info/entry_points.txt
pheval_kghg-0.0.0.dist-info/RECORD
